Metadata-Version: 2.2
Name: bcv_exchange
Version: 1.1.0
Summary: Unofficial Python package to retrieve official exchange rates from the Central Bank of Venezuela (BCV) website.
Home-page: https://github.com/NSMichelJ/bcv_exchange
Author: NSMichelJ
Author-email: 
License: MIT
Keywords: bcv,exchange
Classifier: Development Status :: 3 - Alpha
Classifier: Intended Audience :: Developers
Classifier: Topic :: Software Development :: Build Tools
Classifier: License :: OSI Approved :: MIT License
Classifier: Programming Language :: Python :: 3
License-File: LICENSE
Requires-Dist: beautifulsoup4==4.13.3
Requires-Dist: requests==2.32.3
Dynamic: author
Dynamic: classifier
Dynamic: description
Dynamic: description-content-type
Dynamic: home-page
Dynamic: keywords
Dynamic: license
Dynamic: requires-dist
Dynamic: summary
